odoo/addons/mrp_bom_note/README.rst
odoo/addons/mrp_bom_note/__init__.py
odoo/addons/mrp_bom_note/__manifest__.py
odoo/addons/mrp_bom_note/i18n/de.po
odoo/addons/mrp_bom_note/i18n/es.po
odoo/addons/mrp_bom_note/i18n/fi.po
odoo/addons/mrp_bom_note/i18n/fr.po
odoo/addons/mrp_bom_note/i18n/gl.po
odoo/addons/mrp_bom_note/i18n/hr.po
odoo/addons/mrp_bom_note/i18n/hr_HR.po
odoo/addons/mrp_bom_note/i18n/it.po
odoo/addons/mrp_bom_note/i18n/lt.po
odoo/addons/mrp_bom_note/i18n/mrp_bom_note.pot
odoo/addons/mrp_bom_note/i18n/mrp_bom_notes.pot
odoo/addons/mrp_bom_note/i18n/nl_NL.po
odoo/addons/mrp_bom_note/i18n/pt_BR.po
odoo/addons/mrp_bom_note/i18n/ro.po
odoo/addons/mrp_bom_note/i18n/sl.po
odoo/addons/mrp_bom_note/i18n/tr.po
odoo/addons/mrp_bom_note/i18n/tr_TR.po
odoo/addons/mrp_bom_note/i18n/zh_CN.po
odoo/addons/mrp_bom_note/models/__init__.py
odoo/addons/mrp_bom_note/models/mrp_bom.py
odoo/addons/mrp_bom_note/readme/CONTRIBUTORS.rst
odoo/addons/mrp_bom_note/readme/DESCRIPTION.rst
odoo/addons/mrp_bom_note/readme/USAGE.rst
odoo/addons/mrp_bom_note/static/description/icon.png
odoo/addons/mrp_bom_note/static/description/index.html
odoo/addons/mrp_bom_note/tests/__init__.py
odoo/addons/mrp_bom_note/tests/test_mrp_bom_note.py
odoo/addons/mrp_bom_note/views/mrp_bom_view.xml
odoo13_addon_mrp_bom_note-13.0.1.0.1.dev5.dist-info/METADATA
odoo13_addon_mrp_bom_note-13.0.1.0.1.dev5.dist-info/WHEEL
odoo13_addon_mrp_bom_note-13.0.1.0.1.dev5.dist-info/top_level.txt
odoo13_addon_mrp_bom_note-13.0.1.0.1.dev5.dist-info/RECORD
